[{"time": "00:00:03", "phase": " LIFTOFF THE HOLODOWN CLAMPS HAVE RELEASED FALCON 9 AND WE HAVE BEGUN OUR FLIGHT "}, {"time": "00:00:04", "phase": " LIFTOFF THE HOLODOWN CLAMPS HAVE RELEASED FALCON 9 AND WE HAVE BEGUN OUR FLIGHT  "}, {"time": "00:00:05", "phase": " LIFTOFF THE HOLODOWN CLAMPS HAVE RELEASED FALCON 9 AND WE HAVE BEGUN OUR FLIGHT "}, {"time": "00:00:06", "phase": " LIFTOFF THE HOLODOWN CLAMPS HAVE RELEASED FALCON 9 AND WE HAVE BEGUN OUR FLIGHT "}, {"time": "00:00:07", "phase": " LIFTOFF THE HOLODOWN CLAMPS HAVE RELEASED FALCON 9 AND WE HAVE BEGUN OUR FLIGHT "}, {"time": "00:01:15", "phase": " MAX Q MAXIMUM DYNAMIC PRESSURE THIS IS THE LARGEST AMOUNT OF AERODYNAMIC STRESS EXERTED ON THE VEHICLE "}, {"time": "00:01:16", "phase": " MAX Q MAXIMUM DYNAMIC PRESSURE THIS IS THE LARGEST AMOUNT OF AERODYNAMIC STRESS EXERTED ON THE VEHICLE "}, {"time": "00:01:17", "phase": " MAX Q MAXIMUM DYNAMIC PRESSURE THIS IS THE LARGEST AMOUNT OF AERODYNAMIC STRESS EXERTED ON THE VEHICLE "}, {"time": "00:01:18", "phase": " MAX Q MAXIMUM DYNAMIC PRESSURE THIS IS THE LARGEST AMOUNT OF AERODYNAMIC STRESS EXERTED ON THE VEHICLE "}, {"time": "00:01:19", "phase": " MAX Q MAXIMUM DYNAMIC PRESSURE THIS IS THE LARGEST AMOUNT OF AERODYNAMIC STRESS EXERTED ON THE VEHICLE "}, {"time": "00:01:20", "phase": " MAX Q MAXIMUM DYNAMIC PRESSURE THIS IS THE LARGEST AMOUNT OF AERODYNAMIC STRESS EXERTED ON THE VEHICLE  "}, {"time": "00:01:21", "phase": " MAX Q MAXIMUM DYNAMIC PRESSURE THIS IS THE LARGEST AMOUNT OF AERODYNAMIC STRESS EXERTED ON THE VEHICLE "}, {"time": "00:02:39", "phase": " MECO MAIN ENGINE CUTOFF "}, {"time": "00:02:41", "phase": " STAGE SEPARATION STAGE 1 HAS SEPARATED FROM STAGE 2 "}, {"time": "00:02:42", "phase": " STAGE SEPARATION STAGE 1 HAS SEPARATED FROM STAGE 2 "}, {"time": "00:02:43", "phase": " STAGE SEPARATION STAGE 1 HAS SEPARATED FROM STAGE 2 "}, {"time": "00:02:44", "phase": " STAGE SEPARATION STAGE 1 HAS SEPARATED FROM STAGE 2 "}, {"time": "00:02:45", "phase": " STAGE SEPARATION STAGE 1 HAS SEPARATED FROM STAGE 2 "}, {"time": "00:02:46", "phase": " STAGE SEPARATION STAGE 1 HAS SEPARATED FROM STAGE 2 "}, {"time": "00:02:47", "phase": " STAGE SEPARATION STAGE 1 HAS SEPARATED FROM STAGE 2 "}, {"time": "00:02:49", "phase": " SES 1 SECOND ENGINE STARTUP 1"}, {"time": "00:02:50", "phase": " SES 1 SECOND ENGINE STARTUP 1 "}, {"time": "00:02:51", "phase": " SES 1 SECOND ENGINE STARTUP 1 "}, {"time": "00:02:52", "phase": " SES 1 SECOND ENGINE STARTUP 1 "}, {"time": "00:02:53", "phase": " SES 1 SECOND ENGINE STARTUP 1"}, {"time": "00:02:54", "phase": " SES 1 SECOND ENGINE STARTUP 1"}, {"time": "00:03:37", "phase": " FAIRING DEPLOY THE PROTECTIVE NOSECONE AT THE TOP OF THE ROCKET HAS BEEN DEPLOYED"}, {"time": "00:03:38", "phase": " FAIRING DEPLOY THE PROTECTIVE NOSECONE AT THE TOP OF THE ROCKET HAS BEEN DEPLOYED"}, {"time": "00:03:39", "phase": " FAIRING DEPLOY THE PROTECTIVE NOSECONE AT THE TOP OF THE ROCKET HAS BEEN DEPLOYED"}, {"time": "00:03:40", "phase": " FAIRING DEPLOY THE PROTECTIVE NOSECONE AT THE TOP OF THE ROCKET HAS BEEN DEPLOYED"}, {"time": "00:03:41", "phase": " FAIRING DEPLOY THE PROTECTIVE NOSECONE AT THE TOP OF THE ROCKET HAS BEEN DEPLOYED"}, {"time": "00:03:42", "phase": " FAIRING DEPLOY THE PROTECTIVE NOSECONE AT THE TOP OF THE ROCKET HAS BEEN DEPLOYED"}, {"time": "00:03:43", "phase": " FAIRING DEPLOY THE PROTECTIVE NOSECONE AT THE TOP OF THE ROCKET HAS BEEN DEPLOYED"}, {"time": "00:06:28", "phase": " STAGE ENTRY STAGE 1 IS STARTING ITS ENTRY BURN SLOWING IT DOWN FOR ENTRY INTO THE ATMOSPHERE "}, {"time": "00:06:29", "phase": " STAGE ENTRY STAGE 1 IS STARTING ITS ENTRY BURN SLOWING IT DOWN FOR ENTRY INTO THE ATMOSPHERE "}, {"time": "00:06:30", "phase": " STAGE ENTRY STAGE 1 IS STARTING ITS ENTRY BURN SLOWING IT DOWN FOR ENTRY INTO THE ATMOSPHERE "}, {"time": "00:06:31", "phase": " STAGE ENTRY STAGE 1 IS STARTING ITS ENTRY BURN SLOWING IT DOWN FOR ENTRY INTO THE ATMOSPHERE "}, {"time": "00:06:32", "phase": " STAGE ENTRY STAGE 1 IS STARTING ITS ENTRY BURN SLOWING IT DOWN FOR ENTRY INTO THE ATMOSPHERE "}, {"time": "00:06:33", "phase": " STAGE ENTRY STAGE 1 IS STARTING ITS ENTRY BURN SLOWING IT DOWN FOR ENTRY INTO THE ATMOSPHERE "}, {"time": "00:06:34", "phase": " STAGE ENTRY STAGE 1 IS STARTING ITS ENTRY BURN SLOWING IT DOWN FOR ENTRY INTO THE ATMOSPHERE "}, {"time": "00:08:13", "phase": " SECO 1 SECOND ENGINE CUTOFF "}, {"time": "00:08:14", "phase": " SECO 1 SECOND ENGINE CUTOFF "}, {"time": "00:08:15", "phase": " SECO 1 SECOND ENGINE CUTOFF "}, {"time": "00:08:17", "phase": " STAGE 1 LANDING STAGE 1 HAS BEGUN ITS LANDING BURN SLOWING IT FOR TOUCHDOWN AT SEA "}, {"time": "00:08:18", "phase": " STAGE 1 LANDING STAGE 1 HAS BEGUN ITS LANDING BURN SLOWING IT FOR TOUCHDOWN AT SEA "}, {"time": "00:08:19", "phase": " STAGE 1 LANDING STAGE 1 HAS BEGUN ITS LANDING BURN SLOWING IT FOR TOUCHDOWN AT SEA "}, {"time": "00:08:20", "phase": " STAGE 1 LANDING STAGE 1 HAS BEGUN ITS LANDING BURN SLOWING IT FOR TOUCHDOWN AT SEA  "}, {"time": "00:08:21", "phase": " STAGE 1 LANDING STAGE 1 HAS BEGUN ITS LANDING BURN SLOWING IT FOR TOUCHDOWN AT SEA "}, {"time": "00:08:22", "phase": " STAGE 1 LANDING STAGE 1 HAS BEGUN ITS LANDING BURN SLOWING IT FOR TOUCHDOWN AT SEA "}, {"time": "00:26:39", "phase": " SES 2 SECOND ENGINE START 2 "}, {"time": "00:26:40", "phase": " SES 2 SECOND ENGINE START 2 "}, {"time": "00:26:41", "phase": " SES 2 SECOND ENGINE START 2 "}, {"time": "00:26:42", "phase": " SES 2 SECOND ENGINE START 2 "}, {"time": "00:26:43", "phase": " SES 2 SECOND ENGINE START 2 "}, {"time": "00:26:44", "phase": " SES 2 SECOND ENGINE START 2 "}, {"time": "00:26:45", "phase": " SES 2 SECOND ENGINE START 2 "}, {"time": "00:27:35", "phase": " SECO 2 SECOND ENGINE CUTOFF 2 "}, {"time": "00:27:36", "phase": " SECO 2 SECOND ENGINE CUTOFF 2 "}, {"time": "00:27:37", "phase": " SECO 2 SECOND ENGINE CUTOFF 2 "}, {"time": "00:27:38", "phase": " SECD 2 SECOND ENGINE CUTOFF 2 "}, {"time": "00:27:39", "phase": " SECD 2 SECOND ENGINE CUTOFF 2 "}, {"time": "00:27:40", "phase": " SECD 2 SECOND ENGINE CUTOFF 2 "}, {"time": "00:27:41", "phase": " SECD 2 SECOND ENGINE CUTOFF 2 "}]
